pyd2d.cp311-win32.pyd
pyd2d-0.2.0.dist-info/licenses/LICENSE.txt
pyd2d-0.2.0.dist-info/METADATA
pyd2d-0.2.0.dist-info/WHEEL
pyd2d-0.2.0.dist-info/top_level.txt
pyd2d-0.2.0.dist-info/RECORD
