Metadata-Version: 2.4
Name: pyd2d
Version: 0.2.0
Summary: A Python wrapper for the Windows Direct2D and DirectWrite APIs
License-Expression: MIT
Project-URL: Homepage, https://github.com/merlinz01/pyd2d
Project-URL: Repository, https://github.com/merlinz01/pyd2d
Project-URL: Issues, https://github.com/merlinz01/pyd2d/issues
Classifier: Development Status :: 5 - Production/Stable
Classifier: Environment :: GPU
Classifier: Environment :: Win32 (MS Windows)
Classifier: Intended Audience :: Developers
Classifier: Operating System :: Microsoft :: Windows :: Windows 10
Classifier: Operating System :: Microsoft :: Windows :: Windows 11
Classifier: Programming Language :: Cython
Classifier: Programming Language :: Python :: 3.9
Classifier: Programming Language :: Python :: 3.10
Classifier: Programming Language :: Python :: 3.11
Classifier: Programming Language :: Python :: 3.12
Classifier: Programming Language :: Python :: 3.13
Classifier: Programming Language :: Python :: 3.14
Classifier: Programming Language :: Python :: Free Threading
Classifier: Topic :: Multimedia :: Graphics :: Presentation
Classifier: Typing :: Typed
Requires-Python: >=3.9
License-File: LICENSE.txt
Dynamic: license-file
